slack_watchman/__init__.py
slack_watchman/__main__.py
slack_watchman/clients/__init__.py
slack_watchman/clients/slack_client.py
slack_watchman/exceptions.py
slack_watchman/loggers.py
slack_watchman/models/__init__.py
slack_watchman/models/auth_vars.py
slack_watchman/models/conversation.py
slack_watchman/models/post.py
slack_watchman/models/signature.py
slack_watchman/models/user.py
slack_watchman/models/workspace.py
slack_watchman/signature_downloader.py
slack_watchman/utils.py
slack_watchman/watchman_processor.py
slack_watchman-4.4.3.dist-info/METADATA
slack_watchman-4.4.3.dist-info/WHEEL
slack_watchman-4.4.3.dist-info/entry_points.txt
slack_watchman-4.4.3.dist-info/licenses/LICENSE
slack_watchman-4.4.3.dist-info/RECORD
