Metadata-Version: 2.4
Name: slack-watchman
Version: 4.4.3
Summary: Monitoring and enumerating Slack for exposed secrets
License: GPL-3.0
License-File: LICENSE
Keywords: audit,slack,slack-watchman,watchman,blue-team,red-team,threat-hunting
Author: PaperMtn
Author-email: me@papermtn.co.uk
Requires-Python: >=3.10
Classifier: Intended Audience :: Information Technology
Classifier: License :: OSI Approved :: GNU General Public License v3 (GPLv3)
Classifier: Programming Language :: Python :: 3
Classifier: Programming Language :: Python :: 3.10
Classifier: Programming Language :: Python :: 3.11
Classifier: Programming Language :: Python :: 3.12
Classifier: Programming Language :: Python :: 3.13
Classifier: Programming Language :: Python :: 3.14
Requires-Dist: beautifulsoup4 (>=4.13.4,<5.0.0)
Requires-Dist: colorama (>=0.4.6,<0.5.0)
Requires-Dist: pyyaml (>=6.0.2,<7.0.0)
Requires-Dist: requests (>=2.32.4,<3.0.0)
Project-URL: Blog, https://papermtn.co.uk/tag/slack-watchman/
Project-URL: Homepage, https://github.com/PaperMtn/slack-watchman
Project-URL: Repository, https://github.com/PaperMtn/slack-watchman
